MANIFEST.in
README.md
cirrus.conf
requirements.txt
setup.cfg
setup.py
./btcmarkets/__init__.py
./btcmarkets/api.py
./btcmarkets/compat.py
./btcmarkets/enums.py
./btcmarkets/util.py
./tests/__init__.py
./tests/conftest.py
./tests/test_api.py
btcmarkets.egg-info/PKG-INFO
btcmarkets.egg-info/SOURCES.txt
btcmarkets.egg-info/dependency_links.txt
btcmarkets.egg-info/requires.txt
btcmarkets.egg-info/top_level.txt