Metadata-Version: 1.1
Name: btcmarkets
Version: 0.0.7
Summary: PACKAGE DESCRIPTION HERE
Home-page: https://github.com/limx0/btcmarkets
Author: bradleymcelroy
Author-email: bradley.mcelroy@live.com
License: UNKNOWN
Platform: UNKNOWN
Provides: btcmarkets
Provides: tests
